aiocqhttp/__init__.py
aiocqhttp/api.py
aiocqhttp/api.pyi
aiocqhttp/api_impl.py
aiocqhttp/bus.py
aiocqhttp/connection.py
aiocqhttp/default.py
aiocqhttp/event.py
aiocqhttp/exceptions.py
aiocqhttp/message.py
aiocqhttp/typing.py
aiocqhttp/utils.py
aiocqhttp_sanic-1.2.3.dist-info/LICENSE
aiocqhttp_sanic-1.2.3.dist-info/METADATA
aiocqhttp_sanic-1.2.3.dist-info/WHEEL
aiocqhttp_sanic-1.2.3.dist-info/top_level.txt
aiocqhttp_sanic-1.2.3.dist-info/RECORD
