Metadata-Version: 2.1
Name: aiocqhttp-sanic
Version: 1.2.3
Summary: A Python SDK with async I/O for CQHTTP (Based on Sanic).
Home-page: https://github.com/KawashiroNitori/python-aiocqhttp-sanic
Author: Richard Chien, KawashiroNitori
Author-email: richardchienthebest@gmail.com
License: MIT License
Platform: any
Classifier: Programming Language :: Python :: 3
Classifier: License :: OSI Approved :: MIT License
Classifier: Operating System :: OS Independent
Classifier: Framework :: Robot Framework
Requires-Python: >=3.7
Requires-Dist: sanic (<=19.9.0)
Requires-Dist: httpx (<1.0,>=0.11)
Provides-Extra: all
Requires-Dist: ujson ; extra == 'all'
